README.md
log2tran.py
setup.py
bmp/__init__.py
bmp/parser.py
bmp/plugin/__init__.py
bmp/plugin/common.py
bmp/plugin/miscom.py
log2tran.egg-info/PKG-INFO
log2tran.egg-info/SOURCES.txt
log2tran.egg-info/dependency_links.txt
log2tran.egg-info/top_level.txt